lazy_locker/__init__.py
lazy_locker-0.0.7.dist-info/METADATA
lazy_locker-0.0.7.dist-info/WHEEL
lazy_locker-0.0.7.dist-info/RECORD
