Metadata-Version: 2.4
Name: lazy-locker
Version: 0.0.7
Summary: Python SDK for lazy-locker - A secure local secrets manager
Project-URL: Homepage, https://github.com/WillIsback/lazy-locker
Project-URL: Documentation, https://github.com/WillIsback/lazy-locker#readme
Project-URL: Repository, https://github.com/WillIsback/lazy-locker
Author-email: William Derue <william.derue@gmail.com>
License-Expression: MIT
Classifier: Development Status :: 4 - Beta
Classifier: Intended Audience :: Developers
Classifier: License :: OSI Approved :: MIT License
Classifier: Programming Language :: Python :: 3
Classifier: Programming Language :: Python :: 3.8
Classifier: Programming Language :: Python :: 3.9
Classifier: Programming Language :: Python :: 3.10
Classifier: Programming Language :: Python :: 3.11
Classifier: Programming Language :: Python :: 3.12
Classifier: Topic :: Security
Classifier: Topic :: Software Development :: Libraries :: Python Modules
Requires-Python: >=3.8
